{
  "Tú te ........................... abrigo cuando hace frío. (pongo – pones – pone)": "pones",
  "¿ ........................... pone Julia cuando hace frío? (Cuándo – Cuánto – Qué)": "Qué",
  "Hoy........................... calor. (está – hace – es)": "hace",
  "Chema......................... pone unos guantes negros. (me – te – se)": "se",
  "Yo me ......................... el bañador. (pongo – pones – pone)": "pongo",
  "Escribe la frase correcta: ¿pones – Qué – a hora - te?": "¿Qué te pones ahora?",
  "Escribe la frase correcta: pones – botas – las – Te.": "Te pones las botas.",
  "Escribe la palabra diferente: se – me – la – te": "la",
  "Escribe la palabra diferente: tengo – pongo – llevo – pones": "pones",
  "Escribe la palabra diferente: abrigo – frío – gorro – vestido": "frío",
  "Escribe la palabra diferente: calor – jersey – pantalón – guante": "calor",
  "Escribe la palabra diferente: falda – bufanda – gorda – chaqueta": "gorda",
  "Escribe la frase correcta: pongo - gordos – Me – calcetines.": "Me pongo calcetines gordos.",
  "Escribe la frase correcta: ¿hace frío– Qué – cuando – se pone?": "¿Qué se pone cuando hace frío?",
  "Escribe la frase correcta: unos – marrones – Son – botas.": "Son unos botas marrones.",
  "(Me - Te - Se)…………….. pones calcetines azules.": "Te",
  "Me pongo (el – la – las) ………………jersey malva.": "el",
  "Hoy (hace – pone – lleva)…………….…. calor.": "hace",
  "¿(Qué – De qué – Cómo) ……………….se pone Julia?": "Qué",
  "¿........................... te pones en las manos? (De qué – Cuántos – Qué)": "Qué",
  "Cuando hace frío me pongo el ........................... . (abrigo – bañador – camisa)": "abrigo",
  "Yo me pongo ...........................jersey. (la – el – los)": "el",
  "Ana ........................... pone la falda. (te – me – se)": "se",
  "El pantalón corto ........................... marrón. (es – son – eres)": "es",
  "Escribe la frase correcta: el - pones - Te – bañador.": "Te pones el bañador.",
  "Escribe la frase correcta: hace frío– Cuando – el gorro – se pone.": "Cuando hace frío se pone el gorro.",
  "Escribe la frase correcta: gusta – la – Me – piscina.": "Me gusta la piscina.",
  "¿........................... te pones en los pies? (De qué – Cuántos – Qué)": "Qué",
  "Cuando hace calor me pongo la ........................... . (bufanda – gorra – chaqueta)": "gorra",
  "Yo me pongo ...........................pijama. (el – la – las)": "el",
  "Rúben ........................... pone los vaqueros. (te – se – me)": "se",
  "Las botas ........................... negras. (es – son – eres)": "son",
  "Escribe la frase correcta: los - pones - Te – zapatos.": "Te pones los zapatos.",
  "Escribe la frase correcta: hace frío– Cuando – el jersey – se pone.": "Cuando hace frío se pone el jersey.",
  "Escribe la frase correcta: gusta – el – Me – vestido.": "Me gusta el vestido.",
  "¿........................... te pones en la cabeza? (De qué – Cuántos – Qué)": "Qué",
  "Cuando hace calor me pongo el ........................... . (gorro – abrigo – bañador)": "bañador",
  "Yo me pongo ...........................guantes. (el – los – las)": "los",
  "Julia ........................... pone la camiseta. (te – se – me)": "se",
  "Las zapatillas ........................... rojas. (es – son – se)": "son",
  "Escribe la frase correcta: las - pones - Te – botas.": "Te pones las botas.",
  "Escribe la frase correcta: hace frío– Cuando – los deportivos – se pone.": "Cuando hace frío se pone los deportivos.",
  "Escribe la frase correcta: gusta – la – Me – falda.": "Me gusta la falda."
}