{
  "Mets en ordre les lettres : 1- o – s – e – r – u": "soeur",
  "Mets en ordre les lettres : 2- è – e – m – r": "mère",
  "Mets en ordre les lettres : 3- l – e – l – i – m – f – a": "famille",
  "Mets en ordre les lettres : 4- è – l – e – g – r": "règle",
  "Mets en ordre les lettres : 5- u – e – t – t – r – o": "tortue",
  "Écris un mot sous l'image du robot": "un robot",
  "Écris un mot sous l'image de la trousse": "une trousse",
  "Écris un mot sous l'image du ballon": "un ballon",
  "Écris un mot sous l'image de la poupée": "une poupée",
  "Écris un mot sous l'image du chat": "un chat",
  "Mets en ordre les mots pour faire une phrase : 1- frère. – n’ai pas – de – Je": "Je n'ai pas de frère.",
  "Mets en ordre les mots pour faire une phrase : 2- veux ? – Tu – Qu’est-ce que": "Qu'est-ce que tu veux ?",
  "Mets en ordre les mots pour faire une phrase : 3- saxophone. – un – C’est": "C'est un saxophone.",
  "Mets en ordre les mots pour faire une phrase : 4- moto. – une – veux – Je": "Je veux une moto.",
  "Mets en ordre les mots pour faire une phrase : 5- un – ai – ballon. – j’": "J'ai un ballon."
}